{
    "frame_id": "map",
    "map_height": 3115,
    "map_width": 969,
    "origin": {
        "x": -2.596033,
        "y": -24.005749
    },
    "regions": [
        {
            "category": "custom",
            "cleaning_coverage": false,
            "coverage_enabled": false,
            "coverage_params": {
                "allow_unknown": false,
                "headland_width_m": 0.2,
                "min_turn_radius_m": 0.35,
                "overlap_ratio": 0.3,
                "path_velocity_mps": 0.4,
                "repeat_count": 1,
                "row_angle_deg": 0,
                "row_angle_mode": "auto",
                "work_width_m": 0.5
            },
            "id": "reg_1775899537849",
            "intersection_info": "",
            "name": "区域1",
            "obstacle_behavior": "stop",
            "pause_wait_time_sec": 0,
            "polygon_world": [
                {
                    "x": 8.304290282462556,
                    "y": 50.69947449033295
                },
                {
                    "x": 36.60602651809404,
                    "y": 52.60580905542731
                },
                {
                    "x": 37.48587324044529,
                    "y": 39.01706523244708
                },
                {
                    "x": 8.841974390566092,
                    "y": 37.306252161208555
                },
                {
                    "x": 8.206529535534642,
                    "y": 50.650594116868994
                }
            ],
            "rect_world": {
                "max_x": 37.48587324044529,
                "max_y": 52.60580905542731,
                "min_x": 8.206529535534642,
                "min_y": 37.306252161208555
            },
            "remark": "",
            "shape_type": "polygon",
            "speed_limit_mps": 0.8
        }
    ],
    "resolution": 0.05000000074505806,
    "routes": [
        {
            "id": "route_1776001597720",
            "name": "路线1",
            "remark": "",
            "speed_limit_mps": 1,
            "waypoints": [
                {
                    "w": 1,
                    "x": 19.41887535278791,
                    "y": -1.1814435235019545,
                    "z": 0
                },
                {
                    "w": 1,
                    "x": 17.453258535574705,
                    "y": 34.72382367092595,
                    "z": 0
                },
                {
                    "w": 1,
                    "x": 27.150301500493192,
                    "y": 36.03423488240142,
                    "z": 0
                }
            ]
        },
        {
            "id": "route_1777652322430",
            "name": "录制路线3",
            "remark": "",
            "speed_limit_mps": 1,
            "waypoints": [
                {
                    "w": 1,
                    "x": 22.162857591183936,
                    "y": 94.45087334852933,
                    "z": 0
                },
                {
                    "w": 1,
                    "x": 21.865539124455726,
                    "y": 93.41384065569548,
                    "z": 0
                },
                {
                    "w": 1,
                    "x": 21.165522867545903,
                    "y": 92.31356233591882,
                    "z": 0
                },
                {
                    "w": 1,
                    "x": 20.46522440580456,
                    "y": 91.47530307640203,
                    "z": 0
                },
                {
                    "w": 1,
                    "x": 19.110920108779624,
                    "y": 90.00411612506602,
                    "z": 0
                },
                {
                    "w": 1,
                    "x": 17.701293289204475,
                    "y": 88.58526829562457,
                    "z": 0
                }
            ]
        }
    ],
    "version": "1"
}
